gym_dofbot/__init__.py
gym_dofbot/envs/__init__.py
gym_dofbot/envs/dofbot_env.py
gym_dofbot-0.0.3.dist-info/METADATA
gym_dofbot-0.0.3.dist-info/WHEEL
gym_dofbot-0.0.3.dist-info/top_level.txt
gym_dofbot-0.0.3.dist-info/RECORD
