Metadata-Version: 2.1
Name: gym-dofbot
Version: 0.0.3
Summary: A OpenAI Gym Env for Yahboom DOFBOT robotic arm
Home-page: UNKNOWN
Author: Charles Xu
Author-email: xuzheyuan961124@gmail.com
License: UNKNOWN
Platform: UNKNOWN
Classifier: Programming Language :: Python :: 3
Classifier: License :: OSI Approved :: MIT License
Classifier: Operating System :: OS Independent
Requires-Python: >=3.6
Requires-Dist: gym
